<?xml version="1.0" encoding="ISO-8859-1"?>
<Root_Element ID="DAOCUi">

<!-- @@ Edited with the DAoC User Interface Editor v1.78 -->
<!-- @@ Free download available at http://www.bradtownsend.com/daoced -->

  <!-- Load HHelper Interior Images -->

  <!-- By doing it this way I can select Square, Rounded, or None for frame -->

  <Include>HHelperInteriorImages2.xml</Include>

  <!-- Load HHelper Interior templates -->

  <StatusIconTemplate>
    <Name>StatusIcon_HHelper_Interior</Name>
    <TextureName>healerhelper_04</TextureName>
    <TextureStart>
      <X>0</X>
      <Y>0</Y>
    </TextureStart>
    <Width>64</Width>
    <Height>64</Height>
    <MaxLevels>16</MaxLevels>
    <Horizontal>true</Horizontal>
  </StatusIconTemplate>

  <StatusIconTemplate>
    <Name>StatusIcon_HHelper_BG_Interior</Name>
    <TextureName>dialogimages_01</TextureName>
    <TextureStart>
      <X>323</X>
      <Y>197</Y>
    </TextureStart>
    <Width>32</Width>
    <Height>32</Height>
    <MaxLevels>1</MaxLevels>
    <Horizontal>false</Horizontal>
  </StatusIconTemplate>

</Root_Element>
